opencap/__init__.py
opencap/opencap.py
opencap/opencap_test.py
opencap-0.0.2.dist-info/DESCRIPTION.rst
opencap-0.0.2.dist-info/METADATA
opencap-0.0.2.dist-info/RECORD
opencap-0.0.2.dist-info/WHEEL
opencap-0.0.2.dist-info/metadata.json
opencap-0.0.2.dist-info/top_level.txt
