Metadata-Version: 2.0
Name: opencap
Version: 0.0.2
Summary: Tools to help abstract and standardize OpenCAP common functions
Home-page: https://github.com/opencap/python-opencap
Author: Lane Wagner
Author-email: UNKNOWN
License: MIT
Platform: UNKNOWN
